main.py
vaultcli_aaronsood-1.0.1.dist-info/METADATA
vaultcli_aaronsood-1.0.1.dist-info/WHEEL
vaultcli_aaronsood-1.0.1.dist-info/entry_points.txt
vaultcli_aaronsood-1.0.1.dist-info/top_level.txt
vaultcli_aaronsood-1.0.1.dist-info/RECORD
