Metadata-Version: 2.4
Name: vaultcli-aaronsood
Version: 1.0.1
Summary: A simple encrypted password manager CLI in Python
Author-email: Aaron <theaaronsood@gmail.com>
Requires-Dist: bcrypt
Requires-Dist: cryptography
Requires-Dist: pyperclip
